hiera/__init__.py
hiera/benchmarking.py
hiera/hfhub.py
hiera/hiera.py
hiera/hiera_mae.py
hiera/hiera_utils.py
hiera_transformer-0.1.4.dist-info/LICENSE
hiera_transformer-0.1.4.dist-info/LICENSE.models
hiera_transformer-0.1.4.dist-info/METADATA
hiera_transformer-0.1.4.dist-info/WHEEL
hiera_transformer-0.1.4.dist-info/top_level.txt
hiera_transformer-0.1.4.dist-info/RECORD
