Metadata-Version: 2.1
Name: hiera-transformer
Version: 0.1.4
Summary: A fast, powerful, and simple hierarchical vision transformer
Home-page: https://github.com/facebookresearch/hiera
Author: Chaitanya Ryali, Daniel Bolya
License: Apache 2.0
Classifier: Intended Audience :: Developers
Classifier: Intended Audience :: Education
Classifier: Intended Audience :: Science/Research
Classifier: License :: OSI Approved :: Apache Software License
Classifier: Operating System :: OS Independent
Classifier: Programming Language :: Python :: 3
Classifier: Programming Language :: Python :: 3 :: Only
Classifier: Programming Language :: Python :: 3.8
Classifier: Programming Language :: Python :: 3.9
Classifier: Programming Language :: Python :: 3.10
Classifier: Programming Language :: Python :: 3.11
Classifier: Topic :: Scientific/Engineering :: Artificial Intelligence
Requires-Python: >=3.8.0
License-File: LICENSE
License-File: LICENSE.models
Requires-Dist: torch >=1.8.1
Requires-Dist: timm >=0.4.12
Requires-Dist: tqdm
Requires-Dist: packaging
